LICENSE.txt
README.md
setup.cfg
setup.py
aphorism/__init__.py
aphorism/average.py
aphorism/wierd_numbers.py
aphorism.egg-info/PKG-INFO
aphorism.egg-info/SOURCES.txt
aphorism.egg-info/dependency_links.txt
aphorism.egg-info/requires.txt
aphorism.egg-info/top_level.txt
aphorism/basic_functions/__init__.py
aphorism/basic_functions/add.py
aphorism/basic_functions/divide.py
aphorism/basic_functions/multiply.py
aphorism/basic_functions/subtract.py
aphorism/covid_functions/__init__.py
aphorism/covid_functions/cf_add.py
aphorism/covid_functions/cf_divide.py
aphorism/covid_functions/cf_multiply.py
aphorism/covid_functions/cf_subtract.py
aphorism/dashboard_functions/__init__.py
aphorism/dashboard_functions/df_add.py
aphorism/dashboard_functions/df_divide.py
aphorism/dashboard_functions/df_multiply.py
aphorism/dashboard_functions/df_subtract.py
aphorism/data_collection_functions/__init__.py
aphorism/data_collection_functions/dcf_add.py
aphorism/data_collection_functions/dcf_divide.py
aphorism/data_collection_functions/dcf_multiply.py
aphorism/data_collection_functions/dcf_subtract.py
aphorism/graphing_functions/__init__.py
aphorism/graphing_functions/age_acuity_department.py
aphorism/graphing_functions/gf_add.py
aphorism/graphing_functions/gf_divide.py
aphorism/graphing_functions/gf_multiply.py
aphorism/graphing_functions/gf_subtract.py
aphorism/graphing_functions/examples/age_acuity_department_example.parq
aphorism/image_processing_functions/__init__.py
aphorism/image_processing_functions/ipf_add.py
aphorism/image_processing_functions/ipf_divide.py
aphorism/image_processing_functions/ipf_multiply.py
aphorism/image_processing_functions/ipf_subtract.py
aphorism/latex/__init__.py
aphorism/latex/examples/US_States_Visited_2017.xlsx
aphorism/sql/__init__.py
aphorism/sql/examples/fetbrandt.ipynb