Metadata-Version: 2.1
Name: aphorism
Version: 0.0.23
Summary: My first Python package
Home-page: https://pypi.org/project/aphorism
Author: Joshua Fetbrandt
Author-email: abc@gmail.com
License: MIT
Keywords: altair visuals oppe metrics hospital credentialing image text processing python healthcare
Platform: UNKNOWN
Classifier: Development Status :: 3 - Alpha
Classifier: Topic :: Utilities
Classifier: License :: OSI Approved :: MIT License
Classifier: Topic :: Scientific/Engineering :: Visualization
Classifier: Topic :: Software Development :: Documentation
Classifier: Intended Audience :: Education
Classifier: Programming Language :: Python :: 3
Classifier: Operating System :: MacOS :: MacOS X
Classifier: Operating System :: Microsoft :: Windows
Requires-Python: >=3
License-File: LICENSE.txt
